cmo_dataviz/__init__.py
cmo_dataviz/dataviz.py
cmo_dataviz/resources.py
cmo_dataviz/notebooks/Cmotions Dataviz tutorial.ipynb
cmo_dataviz-0.1.2.dist-info/METADATA
cmo_dataviz-0.1.2.dist-info/WHEEL
cmo_dataviz-0.1.2.dist-info/top_level.txt
cmo_dataviz-0.1.2.dist-info/RECORD
