Metadata-Version: 2.1
Name: cmo-dataviz
Version: 0.1.2
Summary: Easily create graphs using custom styling
Home-page: https://Cmotions@dev.azure.com/Cmotions/Packages/_git/cmo_dataviz
Author: Jeanine Schoonemann
Author-email: service@cmotions.nl
Requires-Python: >=3.6
Requires-Dist: matplotlib (>=3.4.2)
Requires-Dist: pandas (>=1.2.4)
Requires-Dist: seaborn (>=0.11.1)
Requires-Dist: networkx (>=2.6.3)
Provides-Extra: dev
Requires-Dist: black ; extra == 'dev'
Requires-Dist: jupyterlab ; extra == 'dev'
Requires-Dist: pytest (==7.4.0) ; extra == 'dev'
Requires-Dist: ipykernel ; extra == 'dev'
Requires-Dist: twine ; extra == 'dev'
Requires-Dist: pydataset (==0.2.0) ; extra == 'dev'
Requires-Dist: pytest-mpl (==0.16.1) ; extra == 'dev'
Requires-Dist: matplotlib (==3.7.1) ; extra == 'dev'
Requires-Dist: pillow (==9.5.0) ; extra == 'dev'
Requires-Dist: networkx (==3.1) ; extra == 'dev'
Requires-Dist: pandas (==2.0.0) ; extra == 'dev'
